eulogy/__init__.py
eulogy/config.py
eulogy/eulogy.py
eulogy-0.2.3.dist-info/licenses/LICENSE
eulogy-0.2.3.dist-info/METADATA
eulogy-0.2.3.dist-info/WHEEL
eulogy-0.2.3.dist-info/top_level.txt
eulogy-0.2.3.dist-info/RECORD
