Metadata-Version: 2.4
Name: eulogy
Version: 0.2.3
Summary: A logging and code tracing library
Author-email: Josh Pilkington <j.pilkington@hotmail.com>
License-Expression: MIT
Project-URL: Source, https://github.com/roganjoshp/eulogy
Classifier: Programming Language :: Python :: 3
Classifier: Operating System :: OS Independent
Requires-Python: >=3.7
License-File: LICENSE
Provides-Extra: dev
Requires-Dist: pytest; extra == "dev"
Requires-Dist: ruff; extra == "dev"
Dynamic: license-file
